xara/__init__.py
xara/__init__.pyi
xara/__main__.py
xara/_analysis.py
xara/_control.py
xara/_new_analysis.py
xara/_node.py
xara/_pattern.py
xara/algorithm.py
xara/auto.py
xara/ddm.py
xara/exe.py
xara/grad.py
xara/helpers.py
xara/invoke.py
xara/load.py
xara/para.py
xara/post.py
xara/prep.py
xara/recorders.py
xara/system.py
xara/test.py
xara/benchmarks/__init__.py
xara/benchmarks/aisc25.py
xara/units/__init__.py
xara/units/__main__.py
xara/units/cgs.py
xara/units/english.py
xara/units/fas.py
xara/units/fks.py
xara/units/fps.py
xara/units/ias.py
xara/units/iks.py
xara/units/ips.py
xara/units/mks.py
xara/units/si.py
xara/units/test.py
xara/units/units.py
xara/units/us.py
xara-0.0.15.dist-info/licenses/LICENSE.txt
xara-0.0.15.dist-info/METADATA
xara-0.0.15.dist-info/WHEEL
xara-0.0.15.dist-info/entry_points.txt
xara-0.0.15.dist-info/top_level.txt
xara-0.0.15.dist-info/RECORD
