Metadata-Version: 2.4
Name: xara
Version: 0.0.15
Summary: Nonlinear finite element analysis.
Author-email: Pacific Earthquake Engineering Research <50180406+claudioperez@users.noreply.github.com>
Project-URL: Repository, https://github.com/peer-open-source/xara
Project-URL: Documentation, https://xara.so
Project-URL: Examples, https://gallery.stairlab.io
Keywords: computational-mechanics,structural-analysis,finite-element-analysis,earthquake,engineering,berkeley
Classifier: Development Status :: 4 - Beta
Classifier: Intended Audience :: Science/Research
Classifier: Intended Audience :: Developers
Classifier: Programming Language :: C
Classifier: Programming Language :: C++
Classifier: Programming Language :: Fortran
Classifier: Programming Language :: Python
Classifier: Programming Language :: Python :: 3
Classifier: Programming Language :: Python :: 3.8
Classifier: Programming Language :: Python :: 3.9
Classifier: Programming Language :: Python :: 3.10
Classifier: Programming Language :: Python :: 3.11
Classifier: Programming Language :: Python :: 3.12
Classifier: Programming Language :: Python :: 3 :: Only
Classifier: Topic :: Software Development
Classifier: Topic :: Scientific/Engineering
Classifier: Operating System :: Microsoft :: Windows
Classifier: Operating System :: POSIX
Classifier: Operating System :: Unix
Classifier: Operating System :: MacOS
License-File: LICENSE.txt
Requires-Dist: opensees>=0.1.27
Requires-Dist: shps
Dynamic: license-file
